./.gitignore
./LICENSE.txt
./PKG-INFO
./README.md
./pyproject.toml
./uv.lock
./.github/workflows/lint.yml
./.github/workflows/publish.yml
./.github/workflows/tests.yml
./.vscode/settings.json
./metaboatrace/models/__init__.py
./metaboatrace/models/boat.py
./metaboatrace/models/race.py
./metaboatrace/models/racer.py
./metaboatrace/models/region.py
./metaboatrace/models/stadium.py
./tests/metaboatrace/models/test_boat.py
./tests/metaboatrace/models/test_racer.py
./tests/metaboatrace/models/test_region.py
./tests/metaboatrace/models/test_stadium.py
./tests/metaboatrace/models/race/test_bettings.py
./tests/metaboatrace/models/race/test_race_entries.py
./tests/metaboatrace/models/race/test_races.py
metaboatrace_models-2.3.7.dist-info/METADATA
metaboatrace_models-2.3.7.dist-info/WHEEL
metaboatrace_models-2.3.7.dist-info/licenses/LICENSE.txt
metaboatrace_models-2.3.7.dist-info/RECORD
