Metadata-Version: 2.4
Name: metaboatrace.models
Version: 2.3.7
Summary: Models of Japanese boatrace
Author-email: k0kishima <okishimaxyz@gmail.com>
License-Expression: MIT
License-File: LICENSE.txt
Requires-Python: >=3.11
Requires-Dist: pydantic>=2.0.3
Provides-Extra: dev
Requires-Dist: black>=23.7.0; extra == 'dev'
Requires-Dist: codecov>=2.1.13; extra == 'dev'
Requires-Dist: mypy>=1.10.1; extra == 'dev'
Requires-Dist: pytest-cov>=4.1.0; extra == 'dev'
Requires-Dist: pytest>=7.4.0; extra == 'dev'
